{"nBlazeSimVer":1,"src":"start:\nSTORE s0, (s1)\nOUTPUT s0, 3\nADD s1, 1\nCOMP s1, 20\nJUMP C, up\n\nl2:\nINPUT s0, 3\nSTORE s0, (s1)\nADD s1, 1\nINPUT s0, 4\nCOMP s0, 0\nJUMP NZ, l2\n\nendend: JUMP endend\n\nup: ADD s0, 8\nJUMP start\n","debug":{"timescale":100,"brakepoints":[11]},"sim":{"reg":[0,0,0,0,0,0,0,0,0,0,0,0,0,0,0,0],"dmem":[0,0,0,0,0,0,0,0,0,0,0,0,0,0,0,0,0,0,0,0,0,0,0,0,0,0,0,0,0,0,0,0,0,0,0,0,0,0,0,0,0,0,0,0,0,0,0,0,0,0,0,0,0,0,0,0,0,0,0,0,0,0,0,0],"stack":[],"PC":0,"ZF":false,"CF":false,"intEn":true,"intRq":false},"mods":[{"name":"StackMod","addr":["3","4"],"opts":{"size":32},"state":{"stack":[]},"enInt":false}]}