{"nBlazeSimVer":1,"src":"LOAD s0, 1\n\nstart:\nLOAD s1, 8\n\nl:\nOUTPUT s0, (s1)\nADD s1, 1\nRL s0\nCOMP s1, 10\nJUMP C, l\n\nLOAD s1, 8\n\nl2:\nINPUT s0, (s1)\nSTORE s0, (s1)\nADD s1, 1\nCOMP s1, 10\nJUMP C, l2\n\nJUMP start\n","debug":{"timescale":100,"brakepoints":[]},"sim":{"reg":[0,0,0,0,0,0,0,0,0,0,0,0,0,0,0,0],"dmem":[0,0,0,0,0,0,0,0,0,0,0,0,0,0,0,0,0,0,0,0,0,0,0,0,0,0,0,0,0,0,0,0,0,0,0,0,0,0,0,0,0,0,0,0,0,0,0,0,0,0,0,0,0,0,0,0,0,0,0,0,0,0,0,0],"stack":[],"PC":0,"ZF":false,"CF":false,"intEn":true},"mods":[{"name":"MemMapMod","addr":["8-15"],"opts":{"size":8},"state":{"data":[0,0,0,0,0,0,0,0]}}]}